{
    "battlefield": "",
    "code": "bound-soul",
    "conjuration_limit": 0,
    "cost": "[main-action] 1[ceremonial-class]",
    "dice_basic": 0,
    "dice_ceremonial": 1,
    "dice_charm": 0,
    "dice_divine": 0,
    "dice_illusion": 0,
    "dice_natural": 0,
    "dice_sympathy": 0,
    "life": "",
    "pack_code": "ashes",
    "placement_code": "discard",
    "specific_code": null,
    "spellboard": "",
    "subtype_code": "action",
    "text": "<ex>Search your discard pile for an ally and place it into your hand.<\/ex>",
    "title": "Bound Soul",
    "type_code": "spell",
    "unit_attack": "",
    "unit_life": "",
    "unit_recover": ""
}